observations/__init__.py
observations/abalone.py
observations/boston_housing.py
observations/caltech101_silhouettes.py
observations/celeba.py
observations/celegans.py
observations/cifar10.py
observations/cifar100.py
observations/crabs.py
observations/enwik8.py
observations/fashion_mnist.py
observations/insteval.py
observations/iris.py
observations/jsb_chorales.py
observations/karate.py
observations/lsun.py
observations/mnist.py
observations/multi_mnist.py
observations/nips.py
observations/ptb.py
observations/sick.py
observations/small32_imagenet.py
observations/small64_imagenet.py
observations/snli.py
observations/stanford_sentiment_treebank.py
observations/svhn.py
observations/text8.py
observations/util.py
observations/version.py
observations/wikitext103.py
observations/wikitext2.py
observations/wine.py
observations/yelp17.py
observations/r/__init__.py
observations/r/abbey.py
observations/r/ability.py
observations/r/absentee.py
observations/r/accdeaths.py
observations/r/accident.py
observations/r/acf1.py
observations/r/acme.py
observations/r/adler.py
observations/r/admit.py
observations/r/admnrev.py
observations/r/affairs.py
observations/r/affect.py
observations/r/agefat.py
observations/r/agriculture.py
observations/r/aids.py
observations/r/aids2.py
observations/r/air_accs.py
observations/r/air_passengers.py
observations/r/aircondit.py
observations/r/aircondit7.py
observations/r/aircraft.py
observations/r/airfare.py
observations/r/airline.py
observations/r/airmay.py
observations/r/airmiles.py
observations/r/airq.py
observations/r/airquality.py
observations/r/ais.py
observations/r/alcohol.py
observations/r/alcohol1.py
observations/r/aldh2.py
observations/r/alfalfa.py
observations/r/allbacks.py
observations/r/alloauto.py
observations/r/allograft.py
observations/r/ambient_noxch.py
observations/r/amis.py
observations/r/aml.py
observations/r/ams_survey.py
observations/r/anesthetic.py
observations-0.1.4.dist-info/DESCRIPTION.rst
observations-0.1.4.dist-info/METADATA
observations-0.1.4.dist-info/RECORD
observations-0.1.4.dist-info/WHEEL
observations-0.1.4.dist-info/metadata.json
observations-0.1.4.dist-info/top_level.txt
